[
	{
		"English": "Red",
		"Japanese": "赤",
		"Furigana": "あか",
		"Romaji": "Aka",
		"Katakana": "レッド",
		"color":"0xff0000"
	},
	{
		"English": "Orange",
		"Japanese": "橙色",
		"Furigana": "だいだいいろ",
		"Romaji": "Daidaiiro",
		"Katakana": "オレンジ",
		"color": "0xff8800"
	},
	{
		"English": "Yellow",
		"Japanese": "黄色",
		"Furigana": "きいろ",
		"Romaji": "Kiiro",
		"Katakana": "イエロー",
		"color":"0xffff00"
	},
	{
		"English": "Green",
		"Japanese": "緑",
		"Furigana": "みどり",
		"Romaji": "Midori",
		"Katakana": "グリーン",
		"color":"0x00ff00"
	},
	{
		"English": "Blue",
		"Japanese": "青",
		"Furigana": "あお",
		"Romaji": "Ao",
		"Katakana": "ブルー",
		"color":"0x0000ff"
	},
	{
		"English": "Purple",
		"Japanese": "紫",
		"Furigana": "むらさき",
		"Romaji": "Murasaki",
		"Katakana": "パープル",
		"color":"0xff00ff"
	},
	{
		"English": "Pink",
		"Japanese": "桃色",
		"Furigana": "ももいろ",
		"Romaji": "Momoiro",
		"Katakana": "ピンク",
		"color":"0xffaaaa"
	},
	{
		"English": "Brown",
		"Japanese": "茶色",
		"Furigana": "ちゃいろ",
		"Romaji": "Chairo",
		"Katakana": "ブラウン",
		"color":"0x774342"
	},
	{
		"English": "Grey",
		"Japanese": "灰色",
		"Furigana": "はいいろ",
		"Romaji": "Haiiro",
		"Katakana": "グレイ",
		"color":"0xaaaaaa"
	},
	{
		"English": "Black",
		"Japanese": "黒",
		"Furigana": "くろ",
		"Romaji": "Kuro",
		"Katakana": "ブラック",
		"color":"0x000000"
	},
	{
		"English": "White",
		"Japanese": "白",
		"Furigana": "しろ",
		"Romaji": "Shiro",
		"Katakana": "ホワイト",
		"color":"0xFFFFFF"
	}
]
